MANIFEST.in
README.md
setup.py
negentropy/M6502.py
negentropy/M6502decoder.py
negentropy/__init__.py
negentropy/cbmbasic.py
negentropy/cbmbasicdecoder.py
negentropy/cbmcodec.py
negentropy/data.py
negentropy/decoders.py
negentropy/dontcaredecoder.py
negentropy/errors.py
negentropy/gfx.py
negentropy/index.py
negentropy/interval.py
negentropy/memmap.py
negentropy/memory.py
negentropy/multidict.py
negentropy/multiindex.py
negentropy/negentropy.py
negentropy/script.lark
negentropy/scriptparser.py
negentropy/symbols.py
negentropy/templates.py
negentropy.egg-info/PKG-INFO
negentropy.egg-info/SOURCES.txt
negentropy.egg-info/dependency_links.txt
negentropy.egg-info/entry_points.txt
negentropy.egg-info/not-zip-safe
negentropy.egg-info/requires.txt
negentropy.egg-info/top_level.txt
negentropy/symbols/c64.txt
negentropy/templates/content_html.html
negentropy/templates/html.html
negentropy/templates/md.md
negentropy/templates/html/content.html