Metadata-Version: 2.1
Name: negentropy
Version: 0.2
Summary: C64 disassembler
Home-page: https://github.com/shewitt-au/negentropy
Author: Stephen Hewitt
Author-email: retrointernals@gmail.com
License: MIT
Keywords: C64 disassembler 6502 6510
Platform: UNKNOWN
Classifier: Development Status :: 4 - Beta
Classifier: Environment :: Console
Classifier: Intended Audience :: Developers
Classifier: License :: OSI Approved :: MIT License
Classifier: Natural Language :: English
Classifier: Programming Language :: Python :: 3 :: Only
Classifier: Topic :: Games/Entertainment
Classifier: Topic :: Software Development :: Disassemblers
Classifier: Topic :: Utilities
